<annotation>
	<folder>kouraitimonzi</folder>
	<filename>koura58.png</filename>
	<path>/Users/shuichi-fu/Downloads/fish/UnderwaterPhotography/kouraitimonzi/koura58.png</path>
	<source>
		<database>Unknown</database>
	</source>
	<size>
		<width>0</width>
		<height>0</height>
		<depth>3</depth>
	</size>
	<segmented>0</segmented>
	<object>
		<name>smallfish</name>
		<pose>Unspecified</pose>
		<truncated>0</truncated>
		<difficult>0</difficult>
		<bndbox>
			<xmin>291</xmin>
			<ymin>68</ymin>
			<xmax>388</xmax>
			<ymax>137</ymax>
		</bndbox>
	</object>
	<object>
		<name>smallfish</name>
		<pose>Unspecified</pose>
		<truncated>0</truncated>
		<difficult>0</difficult>
		<bndbox>
			<xmin>3</xmin>
			<ymin>148</ymin>
			<xmax>124</xmax>
			<ymax>197</ymax>
		</bndbox>
	</object>
</annotation>
