<annotation>
	<folder>png</folder>
	<filename>koura26.png</filename>
	<path>/Users/shuichi-fu/Downloads/fish/koura/png/koura26.png</path>
	<source>
		<database>Unknown</database>
	</source>
	<size>
		<width>426</width>
		<height>240</height>
		<depth>3</depth>
	</size>
	<segmented>0</segmented>
	<object>
		<name>smallfish</name>
		<pose>Unspecified</pose>
		<truncated>0</truncated>
		<difficult>0</difficult>
		<bndbox>
			<xmin>187</xmin>
			<ymin>128</ymin>
			<xmax>286</xmax>
			<ymax>215</ymax>
		</bndbox>
	</object>
</annotation>
