<annotation>
	<folder>screenshot_img</folder>
	<filename>screensh25.png</filename>
	<path>/Users/shuichi-fu/Documents/yolo_k210_FishDataset/screenshot_img/screensh25.png</path>
	<source>
		<database>Unknown</database>
	</source>
	<size>
		<width>719</width>
		<height>421</height>
		<depth>3</depth>
	</size>
	<segmented>0</segmented>
	<object>
		<name>suzuki</name>
		<pose>Unspecified</pose>
		<truncated>0</truncated>
		<difficult>0</difficult>
		<bndbox>
			<xmin>129</xmin>
			<ymin>44</ymin>
			<xmax>698</xmax>
			<ymax>288</ymax>
		</bndbox>
	</object>
</annotation>
