<annotation>
	<folder>ishidai</folder>
	<filename>ishidai22.png</filename>
	<path>/Users/shuichi-fu/Downloads/fish/ishidai/ishidai22.png</path>
	<source>
		<database>Unknown</database>
	</source>
	<size>
		<width>273</width>
		<height>185</height>
		<depth>3</depth>
	</size>
	<segmented>0</segmented>
	<object>
		<name>azi</name>
		<pose>Unspecified</pose>
		<truncated>0</truncated>
		<difficult>0</difficult>
		<bndbox>
			<xmin>13</xmin>
			<ymin>39</ymin>
			<xmax>238</xmax>
			<ymax>149</ymax>
		</bndbox>
	</object>
</annotation>
