<annotation>
	<folder>misaki_park</folder>
	<filename>misaki101.png</filename>
	<path>/Users/shuichi-fu/Downloads/fish/UnderwaterPhotography/misaki_park/misaki101.png</path>
	<source>
		<database>Unknown</database>
	</source>
	<size>
		<width>0</width>
		<height>0</height>
		<depth>3</depth>
	</size>
	<segmented>0</segmented>
	<object>
		<name>smallfish</name>
		<pose>Unspecified</pose>
		<truncated>0</truncated>
		<difficult>0</difficult>
		<bndbox>
			<xmin>192</xmin>
			<ymin>6</ymin>
			<xmax>292</xmax>
			<ymax>56</ymax>
		</bndbox>
	</object>
	<object>
		<name>smallfish</name>
		<pose>Unspecified</pose>
		<truncated>0</truncated>
		<difficult>0</difficult>
		<bndbox>
			<xmin>373</xmin>
			<ymin>12</ymin>
			<xmax>438</xmax>
			<ymax>54</ymax>
		</bndbox>
	</object>
	<object>
		<name>smallfish</name>
		<pose>Unspecified</pose>
		<truncated>0</truncated>
		<difficult>0</difficult>
		<bndbox>
			<xmin>442</xmin>
			<ymin>54</ymin>
			<xmax>497</xmax>
			<ymax>87</ymax>
		</bndbox>
	</object>
	<object>
		<name>smallfish</name>
		<pose>Unspecified</pose>
		<truncated>0</truncated>
		<difficult>0</difficult>
		<bndbox>
			<xmin>334</xmin>
			<ymin>42</ymin>
			<xmax>393</xmax>
			<ymax>85</ymax>
		</bndbox>
	</object>
	<object>
		<name>smallfish</name>
		<pose>Unspecified</pose>
		<truncated>0</truncated>
		<difficult>0</difficult>
		<bndbox>
			<xmin>326</xmin>
			<ymin>9</ymin>
			<xmax>370</xmax>
			<ymax>38</ymax>
		</bndbox>
	</object>
	<object>
		<name>smallfish</name>
		<pose>Unspecified</pose>
		<truncated>0</truncated>
		<difficult>0</difficult>
		<bndbox>
			<xmin>382</xmin>
			<ymin>49</ymin>
			<xmax>444</xmax>
			<ymax>96</ymax>
		</bndbox>
	</object>
	<object>
		<name>smallfish</name>
		<pose>Unspecified</pose>
		<truncated>0</truncated>
		<difficult>0</difficult>
		<bndbox>
			<xmin>318</xmin>
			<ymin>114</ymin>
			<xmax>353</xmax>
			<ymax>146</ymax>
		</bndbox>
	</object>
	<object>
		<name>smallfish</name>
		<pose>Unspecified</pose>
		<truncated>0</truncated>
		<difficult>0</difficult>
		<bndbox>
			<xmin>138</xmin>
			<ymin>135</ymin>
			<xmax>219</xmax>
			<ymax>185</ymax>
		</bndbox>
	</object>
	<object>
		<name>smallfish</name>
		<pose>Unspecified</pose>
		<truncated>0</truncated>
		<difficult>0</difficult>
		<bndbox>
			<xmin>77</xmin>
			<ymin>49</ymin>
			<xmax>152</xmax>
			<ymax>100</ymax>
		</bndbox>
	</object>
	<object>
		<name>smallfish</name>
		<pose>Unspecified</pose>
		<truncated>0</truncated>
		<difficult>0</difficult>
		<bndbox>
			<xmin>241</xmin>
			<ymin>53</ymin>
			<xmax>299</xmax>
			<ymax>142</ymax>
		</bndbox>
	</object>
	<object>
		<name>smallfish</name>
		<pose>Unspecified</pose>
		<truncated>0</truncated>
		<difficult>0</difficult>
		<bndbox>
			<xmin>357</xmin>
			<ymin>244</ymin>
			<xmax>442</xmax>
			<ymax>295</ymax>
		</bndbox>
	</object>
	<object>
		<name>smallfish</name>
		<pose>Unspecified</pose>
		<truncated>0</truncated>
		<difficult>0</difficult>
		<bndbox>
			<xmin>459</xmin>
			<ymin>293</ymin>
			<xmax>554</xmax>
			<ymax>336</ymax>
		</bndbox>
	</object>
	<object>
		<name>smallfish</name>
		<pose>Unspecified</pose>
		<truncated>0</truncated>
		<difficult>0</difficult>
		<bndbox>
			<xmin>471</xmin>
			<ymin>236</ymin>
			<xmax>569</xmax>
			<ymax>297</ymax>
		</bndbox>
	</object>
	<object>
		<name>smallfish</name>
		<pose>Unspecified</pose>
		<truncated>0</truncated>
		<difficult>0</difficult>
		<bndbox>
			<xmin>493</xmin>
			<ymin>96</ymin>
			<xmax>547</xmax>
			<ymax>127</ymax>
		</bndbox>
	</object>
	<object>
		<name>smallfish</name>
		<pose>Unspecified</pose>
		<truncated>0</truncated>
		<difficult>0</difficult>
		<bndbox>
			<xmin>383</xmin>
			<ymin>97</ymin>
			<xmax>421</xmax>
			<ymax>126</ymax>
		</bndbox>
	</object>
	<object>
		<name>smallfish</name>
		<pose>Unspecified</pose>
		<truncated>0</truncated>
		<difficult>0</difficult>
		<bndbox>
			<xmin>408</xmin>
			<ymin>104</ymin>
			<xmax>460</xmax>
			<ymax>140</ymax>
		</bndbox>
	</object>
	<object>
		<name>smallfish</name>
		<pose>Unspecified</pose>
		<truncated>0</truncated>
		<difficult>0</difficult>
		<bndbox>
			<xmin>273</xmin>
			<ymin>239</ymin>
			<xmax>327</xmax>
			<ymax>283</ymax>
		</bndbox>
	</object>
</annotation>
